setup.cfg
setup.py
pybitid/__init__.py
pybitid/bitid.py
pybitid/pybitcointools.py
pybitid/pysix.py
pybitid.egg-info/PKG-INFO
pybitid.egg-info/SOURCES.txt
pybitid.egg-info/dependency_links.txt
pybitid.egg-info/top_level.txt
pybitid/tests/__init__.py
pybitid/tests/pybitid_test.py