Metadata-Version: 1.1
Name: pybitid
Version: 0.0.4
Summary: Python BitId Library
Home-page: https://www.github.com/LaurentMT/pybitid
Author: laurentmt
Author-email: llll@lll.com
License: UNKNOWN
Download-URL: https://www.github.com/LaurentMT/pybitid/tarball/0.0.4
Keywords: authentication,bitcoin,privacy
Platform: UNKNOWN
Classifier: Development Status :: 3 - Alpha
Classifier: Intended Audience :: Developers
Classifier: License :: OSI Approved :: MIT License
Classifier: Natural Language :: English
Classifier: Programming Language :: Python :: 2.7
Classifier: Programming Language :: Python :: 3.3
Classifier: Topic :: Security
